camoufox/__init__.py
camoufox/__main__.py
camoufox/__version__.py
camoufox/addons.py
camoufox/async_api.py
camoufox/browserforge.yml
camoufox/exceptions.py
camoufox/fingerprints.py
camoufox/fonts.json
camoufox/ip.py
camoufox/launchServer.js
camoufox/locale.py
camoufox/pkgman.py
camoufox/py.typed
camoufox/server.py
camoufox/setup.cfg
camoufox/sync_api.py
camoufox/territoryInfo.xml
camoufox/utils.py
camoufox/virtdisplay.py
camoufox/warnings.py
camoufox/warnings.yml
camoufox/webgl/__init__.py
camoufox/webgl/sample.py
camoufox/webgl/webgl_data.db
camoufox-0.4.10.dist-info/METADATA
camoufox-0.4.10.dist-info/WHEEL
camoufox-0.4.10.dist-info/entry_points.txt
camoufox-0.4.10.dist-info/RECORD
