Metadata-Version: 2.3
Name: camoufox
Version: 0.4.10
Summary: Wrapper around Playwright to help launch Camoufox
License: MIT
Keywords: client,fingerprint,browser,scraping,injector,firefox,playwright
Author: daijro
Author-email: daijro.dev@gmail.com
Requires-Python: >=3.8,<4.0
Classifier: License :: OSI Approved :: MIT License
Classifier: Programming Language :: Python :: 3
Classifier: Programming Language :: Python :: 3.8
Classifier: Programming Language :: Python :: 3.9
Classifier: Programming Language :: Python :: 3.10
Classifier: Programming Language :: Python :: 3.11
Classifier: Programming Language :: Python :: 3.12
Classifier: Programming Language :: Python :: 3.13
Classifier: Topic :: Internet :: WWW/HTTP
Classifier: Topic :: Internet :: WWW/HTTP :: Browsers
Classifier: Topic :: Software Development :: Libraries :: Python Modules
Provides-Extra: geoip
Requires-Dist: browserforge (>=1.2.1,<2.0.0)
Requires-Dist: click
Requires-Dist: geoip2 ; extra == "geoip"
Requires-Dist: language-tags
Requires-Dist: lxml
Requires-Dist: numpy
Requires-Dist: orjson
Requires-Dist: platformdirs
Requires-Dist: playwright
Requires-Dist: pysocks
Requires-Dist: pyyaml
Requires-Dist: requests
Requires-Dist: screeninfo
Requires-Dist: tqdm
Requires-Dist: typing_extensions
Requires-Dist: ua_parser
Project-URL: Homepage, https://camoufox.com/python
Project-URL: Repository, https://github.com/daijro/camoufox
